Metadata-Version: 2.1
Name: microjoy
Version: 0.0.2
Summary: biblioteca para leitura de joystick com micropython
Home-page: UNKNOWN
Author: Issei momonge
Author-email: mggyggf@gmail.com
License: MIT License
Keywords: joystick micropython
Platform: UNKNOWN
License-File: LICENCE
